metargs.py
setup.py
metargs.egg-info/PKG-INFO
metargs.egg-info/SOURCES.txt
metargs.egg-info/dependency_links.txt
metargs.egg-info/requires.txt
metargs.egg-info/top_level.txt