Metadata-Version: 1.0
Name: metargs
Version: 0.1
Summary: Library that supports configuration using a combination of config files and command line arguments
Home-page: UNKNOWN
Author: Calen Pennington
Author-email: cpennington@wgen.net
License: UNKNOWN
Platform: UNKNOWN
